tdc.py
todoist_tdc-0.3.1.dist-info/licenses/LICENSE
todoist_tdc-0.3.1.dist-info/METADATA
todoist_tdc-0.3.1.dist-info/WHEEL
todoist_tdc-0.3.1.dist-info/entry_points.txt
todoist_tdc-0.3.1.dist-info/top_level.txt
todoist_tdc-0.3.1.dist-info/RECORD
