Metadata-Version: 2.4
Name: todoist-tdc
Version: 0.3.1
Summary: todoist cli
License:                     GNU GENERAL PUBLIC LICENSE
Project-URL: Homepage, https://github.com/pschmitt/tdc
Project-URL: Repository, https://github.com/pschmitt/tdc
Project-URL: Issues, https://github.com/pschmitt/tdc/issues
Keywords: todoist
Requires-Python: >=3.12
License-File: LICENSE
Requires-Dist: regex>=2024.11.6
Requires-Dist: rich-argparse>=1.6.0
Requires-Dist: todoist-api-python>=3.1.0
Requires-Dist: wcwidth>=0.2.13
Dynamic: license-file
